pdistx/__init__.py
pdistx/__main__.py
pdistx/utils/__init__.py
pdistx/utils/path.py
pdistx/utils/source.py
pdistx/utils/zip.py
ppack/__init__.py
ppack/__main__.py
ppack/checks.py
ppack/process.py
ppack/template.py
ppack/transform.py
pvariant/__init__.py
pvariant/__main__.py
pvariant/process.py
pvariant/transform.py
pvendor/__init__.py
pvendor/__main__.py
pvendor/process.py
pvendor/transform.py
pdistx-0.2.10.dist-info/LICENSE
pdistx-0.2.10.dist-info/METADATA
pdistx-0.2.10.dist-info/WHEEL
pdistx-0.2.10.dist-info/entry_points.txt
pdistx-0.2.10.dist-info/top_level.txt
pdistx-0.2.10.dist-info/RECORD
