Metadata-Version: 2.1
Name: pdistx
Version: 0.2.10
Summary: A toolset for distributing Python projects in a convenient way.
Home-page: https://github.com/3dninjas/pdistx
Author: 3D Ninjas GmbH
Author-email: niklas@3dninjas.io
License: GPLv3
Platform: UNKNOWN
Classifier: Programming Language :: Python
Classifier: License :: OSI Approved :: GNU General Public License v3 (GPLv3)
Classifier: Operating System :: OS Independent
Requires-Python: >=3.9
License-File: LICENSE
